smartschool_mcp/__init__.py
smartschool_mcp/__main__.py
smartschool_mcp/server.py
smartschool_mcp-0.1.4.dist-info/METADATA
smartschool_mcp-0.1.4.dist-info/WHEEL
smartschool_mcp-0.1.4.dist-info/entry_points.txt
smartschool_mcp-0.1.4.dist-info/licenses/LICENSE
smartschool_mcp-0.1.4.dist-info/RECORD
