Metadata-Version: 2.4
Name: smartschool-mcp
Version: 0.1.4
Summary: Access Smartschool courses, grades, assignments, and messages through the Model Context Protocol
Project-URL: Homepage, https://github.com/MauroDruwel/Smartschool-MCP
Project-URL: Repository, https://github.com/MauroDruwel/Smartschool-MCP
Project-URL: Issues, https://github.com/MauroDruwel/Smartschool-MCP/issues
Author-email: Mauro Druwel <mauro.druwel@gmail.com>
License: MIT
License-File: LICENSE
Classifier: Development Status :: 3 - Alpha
Classifier: Intended Audience :: Developers
Classifier: Intended Audience :: Education
Classifier: License :: OSI Approved :: MIT License
Classifier: Programming Language :: Python :: 3
Classifier: Programming Language :: Python :: 3.13
Classifier: Topic :: Education
Classifier: Topic :: Internet :: WWW/HTTP :: Dynamic Content
Requires-Python: >=3.13
Requires-Dist: mcp[cli]>=1.9.4
Requires-Dist: smartschool
Provides-Extra: dev
Requires-Dist: black>=23.0; extra == 'dev'
Requires-Dist: mypy>=1.0; extra == 'dev'
Requires-Dist: pytest-cov>=4.0; extra == 'dev'
Requires-Dist: pytest>=7.0; extra == 'dev'
Requires-Dist: ruff>=0.1.0; extra == 'dev'
